inputter_tyedee/__init__.py
inputter_tyedee/condition.py
inputter_tyedee/handler.py
inputter_tyedee/inputter.py
inputter_tyedee-1.0.0.dist-info/METADATA
inputter_tyedee-1.0.0.dist-info/WHEEL
inputter_tyedee-1.0.0.dist-info/licenses/LICENSE
inputter_tyedee-1.0.0.dist-info/RECORD
