Metadata-Version: 2.3
Name: inputter_tyedee
Version: 1.0.0
Summary: A library for user input processing.
Project-URL: Homepage, https://github.com/TyedeeGit/inputter
Project-URL: Issues, https://github.com/TyedeeGit/inputter/issues
Author-email: Tyedee <tyedee09@gmail.com>
License-File: LICENSE
Classifier: License :: OSI Approved :: MIT License
Classifier: Operating System :: OS Independent
Classifier: Programming Language :: Python :: 3
Requires-Python: >=3.8
